Metadata-Version: 1.1
Name: habitica-challenge-wrangler
Version: 2.0.0
Summary: Habitica Challenge Data Wrangler - pick winners from challenge data
Home-page: https://github.com/DC23/habitica-challenge-wrangler
Author: JugglinDan
Author-email: jugglindan@gmail.com
License: Apache 2.0
Keywords: Habitica,HabitRPG
Platform: any
Classifier: Development Status :: 4 - Beta
Classifier: Programming Language :: Python :: 2
Classifier: Programming Language :: Python :: 2.7
Classifier: Programming Language :: Python :: 3
Classifier: Environment :: Console
Classifier: Intended Audience :: End Users/Desktop
Classifier: License :: OSI Approved :: Apache Software License
Classifier: Operating System :: OS Independent
Classifier: Topic :: Games/Entertainment :: Role-Playing
Classifier: Topic :: Utilities
